rillrate-0.40.0.dist-info/METADATA
rillrate-0.40.0.dist-info/WHEEL
rillrate/expansion.py
rillrate/__init__.py
rillrate/rillrate.cp36-win_amd64.pyd
rillrate-0.40.0.dist-info/RECORD
