Metadata-Version: 2.1
Name: rillrate
Version: 0.40.0
Summary: rillrate bindings for python
Keywords: logging
Home-Page: https://github.com/rate-technology/rillrate-py
Author: Denis Kolodin <deniskolodin@gmail.com>
Author-Email: Denis Kolodin <deniskolodin@gmail.com>
License: Apache-2.0
